MANIFEST.in
README.rst
setup.py
thrift4p/__init__.py
thrift4p/thrift4p.py
thrift4p/utils.py
thrift4p.egg-info/PKG-INFO
thrift4p.egg-info/SOURCES.txt
thrift4p.egg-info/dependency_links.txt
thrift4p.egg-info/not-zip-safe
thrift4p.egg-info/requires.txt
thrift4p.egg-info/top_level.txt
thrift4p/gen-py/__init__.py
thrift4p/gen-py/bds_es_proxy/ESProxyService.py
thrift4p/gen-py/bds_es_proxy/__init__.py
thrift4p/gen-py/bds_es_proxy/constants.py
thrift4p/gen-py/bds_es_proxy/ttypes.py
thrift4p/gen-py/bds_user_tags/UserTagsManageService.py
thrift4p/gen-py/bds_user_tags/__init__.py
thrift4p/gen-py/bds_user_tags/constants.py
thrift4p/gen-py/bds_user_tags/ttypes.py
thrift4p/gen-py/cms_service/CmsService.py
thrift4p/gen-py/cms_service/__init__.py
thrift4p/gen-py/cms_service/constants.py
thrift4p/gen-py/cms_service/ttypes.py
thrift4p/gen-py/dm_eta_service/DMEtaService.py
thrift4p/gen-py/dm_eta_service/__init__.py
thrift4p/gen-py/dm_eta_service/constants.py
thrift4p/gen-py/dm_eta_service/ttypes.py
thrift4p/gen-py/dm_operation_hub_service/DmOperationHubService.py
thrift4p/gen-py/dm_operation_hub_service/DmOperationHubService.pyc
thrift4p/gen-py/dm_operation_hub_service/__init__.py
thrift4p/gen-py/dm_operation_hub_service/__init__.pyc
thrift4p/gen-py/dm_operation_hub_service/constants.py
thrift4p/gen-py/dm_operation_hub_service/ttypes.py
thrift4p/gen-py/dm_operation_hub_service/ttypes.pyc
thrift4p/gen-py/dm_proxy_service/DMProxyService.py
thrift4p/gen-py/dm_proxy_service/__init__.py
thrift4p/gen-py/dm_proxy_service/constants.py
thrift4p/gen-py/dm_proxy_service/ttypes.py
thrift4p/gen-py/dm_ride_relationship/RideRelationshipService.py
thrift4p/gen-py/dm_ride_relationship/__init__.py
thrift4p/gen-py/dm_ride_relationship/constants.py
thrift4p/gen-py/dm_ride_relationship/ttypes.py
thrift4p/gen-py/dm_spider_proxy_service/DMSpiderProxyService.py
thrift4p/gen-py/dm_spider_proxy_service/__init__.py
thrift4p/gen-py/dm_spider_proxy_service/constants.py
thrift4p/gen-py/dm_spider_proxy_service/ttypes.py
thrift4p/gen-py/dm_trace_query_service/DmTraceQueryService.py
thrift4p/gen-py/dm_trace_query_service/__init__.py
thrift4p/gen-py/dm_trace_query_service/constants.py
