Metadata-Version: 1.0
Name: thrift4p
Version: 0.17.3
Summary: a python interface for thrift api in didapinche.
Home-page: http://gitlab.didapinche.com/dm/anticheating/tree/master/thrift4p
Author: brown
Author-email: 317787106@qq.com
License: UNKNOWN
Keywords: python thrift didapinche
Platform: UNKNOWN
